kmscrypt/__init__.py
kmscrypt/__main__.py
kmscrypt/crypto.py
py.typed
aws_kms_crypt-3.0.0.dist-info/LICENSE
aws_kms_crypt-3.0.0.dist-info/METADATA
aws_kms_crypt-3.0.0.dist-info/WHEEL
aws_kms_crypt-3.0.0.dist-info/RECORD
