Metadata-Version: 2.1
Name: aws-kms-crypt
Version: 3.0.0
Summary: Utility for encrypting and decrypting secrets with the AWS KMS service
License: MIT
Author: Sami Jaktholm
Author-email: sjakthol@outlook.com
Requires-Python: >=3.8,<4.0
Classifier: License :: OSI Approved :: MIT License
Classifier: Programming Language :: Python :: 3
Classifier: Programming Language :: Python :: 3.8
Classifier: Programming Language :: Python :: 3.9
Classifier: Programming Language :: Python :: 3.10
Classifier: Programming Language :: Python :: 3.11
Classifier: Programming Language :: Python :: 3.12
Requires-Dist: boto3 (>=1.26.13,<2.0.0)
Requires-Dist: cryptography (>=3.4,<43.0)
